[
  {
    "id": "0ac7c490-3915-4b0e-9dd5-6affd3ef2680",
    "data": [
      {
        "text": "nah",
        "userDefined": false
      }
    ],
    "isTemplate": false,
    "count": 0,
    "updated": 1536928323
  },
  {
    "id": "48bfa86c-97a6-4c60-9f82-7f4a904a978f",
    "data": [
      {
        "text": "mm",
        "userDefined": false
      }
    ],
    "isTemplate": false,
    "count": 0,
    "updated": 1536928323
  },
  {
    "id": "30277853-9b4e-4612-ac74-cb6c61827961",
    "data": [
      {
        "text": "perhaps",
        "userDefined": false
      }
    ],
    "isTemplate": false,
    "count": 0,
    "updated": 1536928323
  },
  {
    "id": "1a22b5eb-3a02-49bb-9e20-1523c55c7895",
    "data": [
      {
        "text": "perhams",
        "userDefined": false
      }
    ],
    "isTemplate": false,
    "count": 0,
    "updated": 1536928323
  },
  {
    "id": "ad2a456d-976c-4ede-9a22-af2ce93848d8",
    "data": [
      {
        "text": "yhea",
        "userDefined": false
      }
    ],
    "isTemplate": false,
    "count": 0,
    "updated": 1536921759
  },
  {
    "id": "ff6f59a8-a102-4a9f-8a53-d741480b3bc3",
    "data": [
      {
        "text": "maybe",
        "userDefined": false
      }
    ],
    "isTemplate": false,
    "count": 0,
    "updated": 1536921759
  },
  {
    "id": "0c04feeb-2d8b-4641-b8ef-2f903f199b03",
    "data": [
      {
        "text": "sometimes",
        "userDefined": false
      }
    ],
    "isTemplate": false,
    "count": 0,
    "updated": 1536921759
  },
  {
    "id": "e6533be2-e51f-427b-af7c-a38d9d066015",
    "data": [
      {
        "text": "no",
        "userDefined": false
      }
    ],
    "isTemplate": false,
    "count": 0,
    "updated": 1536921759
  },
  {
    "id": "357375c9-a651-46dd-9198-7cd28e15f7af",
    "data": [
      {
        "text": "yes",
        "userDefined": false
      }
    ],
    "isTemplate": false,
    "count": 0,
    "updated": 1536921759
  }
]